AUTHORS.rst
CHANGES.rst
HGREV
LICENSE.txt
MANIFEST.in
README.rst
TODO.rst
hgcampfire.py
setup.py
hgcampfire.egg-info/PKG-INFO
hgcampfire.egg-info/SOURCES.txt
hgcampfire.egg-info/dependency_links.txt
hgcampfire.egg-info/top_level.txt