Metadata-Version: 1.0
Name: hgcampfire
Version: 0.3
Summary: Mercurial hook to report incoming changesets to Campfire chatroom
Home-page: http://bitbucket.org/markdrago/hgcampfire/
Author: Mark Drago
Author-email: markdrago@gmail.com
License: UNKNOWN
Platform: UNKNOWN
Classifier: Development Status :: 4 - Beta
Classifier: Environment :: Plugins
Classifier: Intended Audience :: Developers
Classifier: License :: OSI Approved :: GNU General Public License (GPL)
Classifier: Operating System :: OS Independent
Classifier: Programming Language :: Python
Classifier: Topic :: Software Development :: Version Control
